[
  {
    "line": 1,
    "elements": [
      {
        "start_timestamp": "2021-03-02T02:57:15.961Z",
        "line": 4,
        "name": "Query for used car",
        "description": "  search for used car and verify that car is available",
        "id": "query-exiting-used-car;query-for-used-car",
        "type": "scenario",
        "keyword": "Scenario",
        "steps": [
          {
            "result": {
              "duration": 7030259500,
              "status": "passed"
            },
            "line": 6,
            "name": "I go to \"https://www.tmsandbox.co.nz/\"",
            "match": {
              "arguments": [
                {
                  "val": "\"https://www.tmsandbox.co.nz/\"",
                  "offset": 8
                }
              ],
              "location": "com.tmsandbox.stepDefinations.StepDefination_QueryUsedCar.goToTMSandboxPage(java.lang.String)"
            },
            "keyword": "Given "
          },
          {
            "result": {
              "duration": 278152300,
              "status": "passed"
            },
            "line": 7,
            "name": "I query for \"1998 BMW 328i E46\" in searchbox",
            "match": {
              "arguments": [
                {
                  "val": "\"1998 BMW 328i E46\"",
                  "offset": 12
                }
              ],
              "location": "com.tmsandbox.stepDefinations.StepDefination_QueryUsedCar.queryForItem(java.lang.String)"
            },
            "keyword": "When "
          },
          {
            "result": {
              "duration": 227888200,
              "status": "passed"
            },
            "line": 8,
            "name": "I click on search button",
            "match": {
              "location": "com.tmsandbox.stepDefinations.StepDefination_QueryUsedCar.clickSearchButton()"
            },
            "keyword": "And "
          },
          {
            "result": {
              "error_message": "org.openqa.selenium.NoSuchElementException: no such element: Unable to locate element: {\"method\":\"xpath\",\"selector\":\"//a/div[@data-listingid\u003d\u00272149213502\u0027]\"}\n  (Session info: chrome\u003d88.0.4324.190)\nFor documentation on this error, please visit: https://www.seleniumhq.org/exceptions/no_such_element.html\nBuild info: version: \u00273.141.59\u0027, revision: \u0027e82be7d358\u0027, time: \u00272018-11-14T08:17:03\u0027\nSystem info: host: \u0027DIKSHA-PC\u0027, ip: \u0027192.168.139.1\u0027, os.name: \u0027Windows 10\u0027, os.arch: \u0027amd64\u0027, os.version: \u002710.0\u0027, java.version: \u002714.0.2\u0027\nDriver info: org.openqa.selenium.chrome.ChromeDriver\nCapabilities {acceptInsecureCerts: false, browserName: chrome, browserVersion: 88.0.4324.190, chrome: {chromedriverVersion: 88.0.4324.96 (68dba2d8a0b14..., userDataDir: C:\\Users\\DIKSHA~1\\AppData\\L...}, goog:chromeOptions: {debuggerAddress: localhost:50897}, javascriptEnabled: true, networkConnectionEnabled: false, pageLoadStrategy: normal, platform: WINDOWS, platformName: WINDOWS, proxy: Proxy(), setWindowRect: true, strictFileInteractability: false, timeouts: {implicit: 0, pageLoad: 300000, script: 30000}, unhandledPromptBehavior: dismiss and notify, webauthn:extension:largeBlob: true, webauthn:virtualAuthenticators: true}\nSession ID: 081c4e99ec55d438cc19aafa1dd0a9e7\n*** Element info: {Using\u003dxpath, value\u003d//a/div[@data-listingid\u003d\u00272149213502\u0027]}\r\n\tat java.base/jdk.internal.reflect.NativeConstructorAccessorImpl.newInstance0(Native Method)\r\n\tat java.base/jdk.internal.reflect.NativeConstructorAccessorImpl.newInstance(NativeConstructorAccessorImpl.java:62)\r\n\tat java.base/jdk.internal.reflect.DelegatingConstructorAccessorImpl.newInstance(DelegatingConstructorAccessorImpl.java:45)\r\n\tat java.base/java.lang.reflect.Constructor.newInstanceWithCaller(Constructor.java:500)\r\n\tat java.base/java.lang.reflect.Constructor.newInstance(Constructor.java:481)\r\n\tat org.openqa.selenium.remote.http.W3CHttpResponseCodec.createException(W3CHttpResponseCodec.java:187)\r\n\tat org.openqa.selenium.remote.http.W3CHttpResponseCodec.decode(W3CHttpResponseCodec.java:122)\r\n\tat org.openqa.selenium.remote.http.W3CHttpResponseCodec.decode(W3CHttpResponseCodec.java:49)\r\n\tat org.openqa.selenium.remote.HttpCommandExecutor.execute(HttpCommandExecutor.java:158)\r\n\tat org.openqa.selenium.remote.service.DriverCommandExecutor.execute(DriverCommandExecutor.java:83)\r\n\tat org.openqa.selenium.remote.RemoteWebDriver.execute(RemoteWebDriver.java:552)\r\n\tat org.openqa.selenium.remote.RemoteWebDriver.findElement(RemoteWebDriver.java:323)\r\n\tat org.openqa.selenium.remote.RemoteWebDriver.findElementByXPath(RemoteWebDriver.java:428)\r\n\tat org.openqa.selenium.By$ByXPath.findElement(By.java:353)\r\n\tat org.openqa.selenium.remote.RemoteWebDriver.findElement(RemoteWebDriver.java:315)\r\n\tat com.tmsandbox.runner.CommonMethods.findElement(CommonMethods.java:66)\r\n\tat com.tmsandbox.stepDefinations.StepDefination_QueryUsedCar.verifySearchedItemPresent(StepDefination_QueryUsedCar.java:51)\r\n\tat ✽.I verify that \"1998 BMW 328i E46\" item is present(file:///D:/Study%20Folder/Java_Workspace/TradeMeSandboxUIAutomation/src/test/resources/features/Scenario1_QueryUsedCar.feature:9)\r\n",
              "duration": 10066724900,
              "status": "failed"
            },
            "line": 9,
            "name": "I verify that \"1998 BMW 328i E46\" item is present",
            "match": {
              "arguments": [
                {
                  "val": "\"1998 BMW 328i E46\"",
                  "offset": 14
                }
              ],
              "location": "com.tmsandbox.stepDefinations.StepDefination_QueryUsedCar.verifySearchedItemPresent(java.lang.String)"
            },
            "keyword": "Then "
          }
        ]
      },
      {
        "start_timestamp": "2021-03-02T02:57:33.638Z",
        "line": 11,
        "name": "Details of used car",
        "description": "\tconfirm that car details are available",
        "id": "query-exiting-used-car;details-of-used-car",
        "type": "scenario",
        "keyword": "Scenario",
        "steps": [
          {
            "result": {
              "duration": 27982500,
              "status": "passed"
            },
            "line": 13,
            "name": "I am on search result page",
            "match": {
              "location": "com.tmsandbox.stepDefinations.StepDefination_QueryUsedCar.checkIfOnSearchResultPage()"
            },
            "keyword": "Given "
          },
          {
            "result": {
              "error_message": "org.openqa.selenium.NoSuchElementException: no such element: Unable to locate element: {\"method\":\"xpath\",\"selector\":\"//a/div[@data-listingid\u003d\u00272149213502\u0027]\"}\n  (Session info: chrome\u003d88.0.4324.190)\nFor documentation on this error, please visit: https://www.seleniumhq.org/exceptions/no_such_element.html\nBuild info: version: \u00273.141.59\u0027, revision: \u0027e82be7d358\u0027, time: \u00272018-11-14T08:17:03\u0027\nSystem info: host: \u0027DIKSHA-PC\u0027, ip: \u0027192.168.139.1\u0027, os.name: \u0027Windows 10\u0027, os.arch: \u0027amd64\u0027, os.version: \u002710.0\u0027, java.version: \u002714.0.2\u0027\nDriver info: org.openqa.selenium.chrome.ChromeDriver\nCapabilities {acceptInsecureCerts: false, browserName: chrome, browserVersion: 88.0.4324.190, chrome: {chromedriverVersion: 88.0.4324.96 (68dba2d8a0b14..., userDataDir: C:\\Users\\DIKSHA~1\\AppData\\L...}, goog:chromeOptions: {debuggerAddress: localhost:50897}, javascriptEnabled: true, networkConnectionEnabled: false, pageLoadStrategy: normal, platform: WINDOWS, platformName: WINDOWS, proxy: Proxy(), setWindowRect: true, strictFileInteractability: false, timeouts: {implicit: 0, pageLoad: 300000, script: 30000}, unhandledPromptBehavior: dismiss and notify, webauthn:extension:largeBlob: true, webauthn:virtualAuthenticators: true}\nSession ID: 081c4e99ec55d438cc19aafa1dd0a9e7\n*** Element info: {Using\u003dxpath, value\u003d//a/div[@data-listingid\u003d\u00272149213502\u0027]}\r\n\tat java.base/jdk.internal.reflect.NativeConstructorAccessorImpl.newInstance0(Native Method)\r\n\tat java.base/jdk.internal.reflect.NativeConstructorAccessorImpl.newInstance(NativeConstructorAccessorImpl.java:62)\r\n\tat java.base/jdk.internal.reflect.DelegatingConstructorAccessorImpl.newInstance(DelegatingConstructorAccessorImpl.java:45)\r\n\tat java.base/java.lang.reflect.Constructor.newInstanceWithCaller(Constructor.java:500)\r\n\tat java.base/java.lang.reflect.Constructor.newInstance(Constructor.java:481)\r\n\tat org.openqa.selenium.remote.http.W3CHttpResponseCodec.createException(W3CHttpResponseCodec.java:187)\r\n\tat org.openqa.selenium.remote.http.W3CHttpResponseCodec.decode(W3CHttpResponseCodec.java:122)\r\n\tat org.openqa.selenium.remote.http.W3CHttpResponseCodec.decode(W3CHttpResponseCodec.java:49)\r\n\tat org.openqa.selenium.remote.HttpCommandExecutor.execute(HttpCommandExecutor.java:158)\r\n\tat org.openqa.selenium.remote.service.DriverCommandExecutor.execute(DriverCommandExecutor.java:83)\r\n\tat org.openqa.selenium.remote.RemoteWebDriver.execute(RemoteWebDriver.java:552)\r\n\tat org.openqa.selenium.remote.RemoteWebDriver.findElement(RemoteWebDriver.java:323)\r\n\tat org.openqa.selenium.remote.RemoteWebDriver.findElementByXPath(RemoteWebDriver.java:428)\r\n\tat org.openqa.selenium.By$ByXPath.findElement(By.java:353)\r\n\tat org.openqa.selenium.remote.RemoteWebDriver.findElement(RemoteWebDriver.java:315)\r\n\tat com.tmsandbox.runner.CommonMethods.clickOnElementUsingActions(CommonMethods.java:42)\r\n\tat com.tmsandbox.stepDefinations.StepDefination_QueryUsedCar.clickOnListItem(StepDefination_QueryUsedCar.java:63)\r\n\tat ✽.I click on \"1998 BMW 328i E46\" item(file:///D:/Study%20Folder/Java_Workspace/TradeMeSandboxUIAutomation/src/test/resources/features/Scenario1_QueryUsedCar.feature:14)\r\n",
              "duration": 10022382200,
              "status": "failed"
            },
            "line": 14,
            "name": "I click on \"1998 BMW 328i E46\" item",
            "match": {
              "arguments": [
                {
                  "val": "\"1998 BMW 328i E46\"",
                  "offset": 11
                }
              ],
              "location": "com.tmsandbox.stepDefinations.StepDefination_QueryUsedCar.clickOnListItem(java.lang.String)"
            },
            "keyword": "When "
          },
          {
            "result": {
              "status": "skipped"
            },
            "line": 15,
            "name": "I verify Number plate",
            "match": {
              "location": "com.tmsandbox.stepDefinations.StepDefination_QueryUsedCar.verifyNumberPlate()"
            },
            "keyword": "Then "
          },
          {
            "result": {
              "duration": 999800,
              "status": "skipped"
            },
            "line": 16,
            "name": "I verify Kilometres",
            "match": {
              "location": "com.tmsandbox.stepDefinations.StepDefination_QueryUsedCar.verifyIfKilometresPresent()"
            },
            "keyword": "And "
          },
          {
            "result": {
              "status": "skipped"
            },
            "line": 17,
            "name": "I verify Body",
            "match": {
              "location": "com.tmsandbox.stepDefinations.StepDefination_QueryUsedCar.verifyIfBodyPresent()"
            },
            "keyword": "And "
          },
          {
            "result": {
              "duration": 1000200,
              "status": "skipped"
            },
            "line": 18,
            "name": "I verify Seats",
            "match": {
              "location": "com.tmsandbox.stepDefinations.StepDefination_QueryUsedCar.verifyIfSeatsPresent()"
            },
            "keyword": "And "
          }
        ]
      }
    ],
    "name": "Query exiting used car",
    "description": "  search for used car and verify deatails",
    "id": "query-exiting-used-car",
    "keyword": "Feature",
    "uri": "file:src/test/resources/features/Scenario1_QueryUsedCar.feature",
    "tags": []
  }
]